blockwork/__init__.py
blockwork/__main__.py
blockwork/activities/__init__.py
blockwork/activities/bootstrap.py
blockwork/activities/common.py
blockwork/activities/exec.py
blockwork/activities/info.py
blockwork/activities/shell.py
blockwork/activities/tools.py
blockwork/bootstrap/__init__.py
blockwork/bootstrap/containers.py
blockwork/bootstrap/registry.py
blockwork/config/__init__.py
blockwork/config/blockwork.py
blockwork/config/common.py
blockwork/containerfiles/foundation/Containerfile
blockwork/containerfiles/foundation/README.md
blockwork/containerfiles/foundation/forwarder/blockwork
blockwork/containers/__init__.py
blockwork/containers/common.py
blockwork/containers/container.py
blockwork/containers/runtime.py
blockwork/context.py
blockwork/foundation.py
blockwork/state.py
blockwork/tools/__init__.py
blockwork/tools/registry.py
blockwork/tools/tool.py
blockwork-1.0.dist-info/LICENSE
blockwork-1.0.dist-info/METADATA
blockwork-1.0.dist-info/WHEEL
blockwork-1.0.dist-info/entry_points.txt
blockwork-1.0.dist-info/RECORD
