Metadata-Version: 2.1
Name: blockwork
Version: 1.0
Summary: An opionated EDA flow
License: Apache-2.0
Requires-Python: >=3.8,<4.0
Classifier: License :: OSI Approved :: Apache Software License
Classifier: Programming Language :: Python :: 3
Classifier: Programming Language :: Python :: 3.8
Classifier: Programming Language :: Python :: 3.9
Classifier: Programming Language :: Python :: 3.10
Classifier: Programming Language :: Python :: 3.11
Requires-Dist: click (>=8.1.3,<9.0.0)
Requires-Dist: docker (>=6.1.2,<7.0.0)
Requires-Dist: poethepoet (>=0.20.0,<0.21.0)
Requires-Dist: pyyaml (>=6.0,<7.0)
Requires-Dist: rich (>=13.3.4,<14.0.0)
